{
  "name": "SITL Default",
  "description": "Default field profile for SITL testing at Zijingang",
  "coordinate_system": "WGS84",
  "boundary": {
    "description": "Test flight area",
    "polygon": [
      {
        "lat": 30.2700,
        "lon": 120.0900
      },
      {
        "lat": 30.2700,
        "lon": 120.1000
      },
      {
        "lat": 30.2600,
        "lon": 120.1000
      },
      {
        "lat": 30.2600,
        "lon": 120.0900
      },
      {
        "lat": 30.2700,
        "lon": 120.0900
      }
    ]
  },
  "landing": {
    "description": "North-south runway approach",
    "touchdown_point": {
      "lat": 30.2610,
      "lon": 120.0950,
      "alt_m": 0.0
    },
    "heading_deg": 180.0,
    "glide_slope_deg": 3.0,
    "approach_alt_m": 30.0,
    "runway_length_m": 200.0,
    "use_do_land_start": true
  },
  "scan": {
    "description": "Lawnmower scan pattern",
    "altitude_m": 80.0,
    "spacing_m": 200.0,
    "heading_deg": 0.0
  },
  "loiter_point": {
    "description": "Default loiter orbit center",
    "lat": 30.2650,
    "lon": 120.0950,
    "alt_m": 80.0,
    "radius_m": 80.0
  },
  "attack_run": {
    "approach_distance_m": 200,
    "exit_distance_m": 200,
    "release_acceptance_radius_m": 0
  },
  "safety_buffer_m": 50.0
}
